pymerc/__init__.py
pymerc/api/base.py
pymerc/api/buildings.py
pymerc/api/businesses.py
pymerc/api/map.py
pymerc/api/models/buildings.py
pymerc/api/models/businesses.py
pymerc/api/models/common.py
pymerc/api/models/map.py
pymerc/api/models/player.py
pymerc/api/models/static.py
pymerc/api/models/towns.py
pymerc/api/models/transports.py
pymerc/api/player.py
pymerc/api/static.py
pymerc/api/towns.py
pymerc/api/transports.py
pymerc/client.py
pymerc/exceptions.py
pymerc/game/building.py
pymerc/game/exports.py
pymerc/game/imports.py
pymerc/game/operation.py
pymerc/game/player.py
pymerc/game/recipe.py
pymerc/game/storehouse.py
pymerc/game/town.py
pymerc/game/transport.py
pymerc/util/data.py
pymerc/util/towns.py
pymerc-0.6.0.dist-info/METADATA
pymerc-0.6.0.dist-info/WHEEL
pymerc-0.6.0.dist-info/RECORD
