Metadata-Version: 2.1
Name: pymerc
Version: 0.6.0
Summary: A Python library for interacting with the Mercatorio browser based game
Home-page: https://github.com/jmgilman/pymerc
License: MIT
Keywords: mercatorio,python,library,game
Author: Joshua Gilman
Author-email: joshuagilman@gmail.com
Requires-Python: >=3.11,<4.0
Classifier: License :: OSI Approved :: MIT License
Classifier: Programming Language :: Python :: 3
Classifier: Programming Language :: Python :: 3.11
Classifier: Programming Language :: Python :: 3.12
Requires-Dist: async-lru (>=2.0.4,<3.0.0)
Requires-Dist: asyncio (>=3.4.3,<4.0.0)
Requires-Dist: httpx[http2] (>=0.27.0,<0.28.0)
Requires-Dist: loguru (>=0.7.2,<0.8.0)
Requires-Dist: pydantic (>=2.7.1,<3.0.0)
